<jamast>
	<model>
		<group name="Group0">
			<_location z="0.0" y="0.0" x="0.0"></_location>
			<_rotation zrotate="0.0" yrotate="0.0" xrotate="0.0"></_rotation>
			<group name="dodai">
				<_location z="0.0" y="0.0" x="0.0"></_location>
				<_rotation zrotate="0.0" yrotate="0.0" xrotate="0.0"></_rotation>
				<_XMLBoxList transparent="true" color="lightGray" zsize="0.02"
					ysize="0.27" xsize="0.02">
					<_location z="0.0" y="-0.21" x="-0.05"></_location>
				</_XMLBoxList>
				<_XMLBoxList transparent="true" color="lightGray" zsize="0.1"
					ysize="0.0050" xsize="0.3">
					<_location z="0.0" y="-0.3475" x="0.0"></_location>
				</_XMLBoxList>
				<_XMLBoxList transparent="true" color="lightGray" zsize="0.02"
					ysize="0.27" xsize="0.02">
					<_location z="0.0" y="-0.21" x="0.05"></_location>
				</_XMLBoxList>
				<_XMLBoxList transparent="true" color="lightGray" zsize="0.07"
					ysize="0.05" xsize="0.54">
					<_location z="0.0" y="-0.05" x="0.0"></_location>
				</_XMLBoxList>
				<group name="daisha">
					<_location z="0.0" y="0.0" x="0.0"></_location>
					<_rotation zrotate="0.0" yrotate="0.0" xrotate="0.0"></_rotation>
					<_linkdataList column="2" const="0.0" target="a"></_linkdataList>
					<_XMLBoxList transparent="true" color="yellow" zsize="0.0050"
						ysize="0.05" xsize="0.07">
						<_location z="0.02" y="0.0" x="0.0"></_location>
					</_XMLBoxList>
					<group name="sinsi">
						<_location z="0.0" y="0.0" x="0.0"></_location>
						<_rotation zrotate="0.0" yrotate="0.0" xrotate="0.0"></_rotation>
						<_linkdataList column="3" const="0.0" target="theta"></_linkdataList>
						<_XMLCylinderList color="red" div="10" height="0.018"
							r="0.01">
							<_rotation zrotate="0.0" yrotate="0.0" xrotate="1.5708"></_rotation>
							<_location z="0.0325" y="0.0" x="0.0"></_location>
						</_XMLCylinderList>
						<_XMLCylinderList color="black" div="10" height="0.3"
							r="0.0025">
							<_location z="0.037" y="0.15" x="0.0"></_location>
						</_XMLCylinderList>
					</group>
				</group>
			</group>
		</group>
	</model>
	<config>
		<_background color="white"></_background>
		<_light z="-0.8" y="-0.8" x="0.2"></_light>
		<_view z="1.0" y="0.0" x="0.0" zrotate="0.0" yrotate="0.0"
			xrotate="-0.2"></_view>
		<_modelUnit length="m" angle="radian"></_modelUnit>
		<_dataUnit length="m" angle="radian"></_dataUnit>
	</config>
</jamast>